detamvc/__init__.py
detamvc/extras/flickr.py
detamvc/generator.py
detamvc/main.py
detamvc/model.py
detamvc/templates/authlib_users/model.py
detamvc/templates/authlib_users/router.py
detamvc/templates/authlib_users/templates/dashboard.html
detamvc/templates/authlib_users/templates/login.html
detamvc/templates/authlib_users/templates/not_authenticated.html
detamvc/templates/authlib_users/templates/signup.html
detamvc/templates/authlib_users/utils.py
detamvc/templates/core/.env
detamvc/templates/core/main.py
detamvc/templates/core/requirements.txt
detamvc/templates/core/static_pages/router.py
detamvc/templates/core/static_pages/static/css/core.css
detamvc/templates/core/static_pages/static/css/stylesheet.css
detamvc/templates/core/static_pages/static/img/logo.svg
detamvc/templates/core/static_pages/static/js/application.js
detamvc/templates/core/static_pages/static/js/color-modes.js
detamvc/templates/core/static_pages/templates/_base.html
detamvc/templates/core/static_pages/templates/_color_mode.html
detamvc/templates/core/static_pages/templates/_navlinks.html
detamvc/templates/core/static_pages/templates/_svg_symbols.html
detamvc/templates/core/static_pages/templates/index.html
detamvc/templates/mkdocs_core/docs/assets/css/extra.css
detamvc/templates/mkdocs_core/docs/assets/img/logo.svg
detamvc/templates/mkdocs_core/docs/index.md
detamvc/templates/mkdocs_core/docs/tutorial/markdown_basics.md
detamvc/templates/mkdocs_core/main.py
detamvc/templates/mkdocs_core/mkdocs.yml
detamvc/templates/mkdocs_core/requirements.txt
detamvc/templates/scaffold/model.py
detamvc/templates/scaffold/router.py
detamvc/templates/scaffold/templates/form.html
detamvc/templates/scaffold/templates/index.html
detamvc/templates/scaffold/templates/view.html
detamvc/templates/scaffold_helpers/bool.html
detamvc/templates/scaffold_helpers/float.html
detamvc/templates/scaffold_helpers/int.html
detamvc/templates/scaffold_helpers/scaffold_navlink.html
detamvc/templates/scaffold_helpers/str.html
detamvc-0.5.0.dist-info/entry_points.txt
detamvc-0.5.0.dist-info/METADATA
detamvc-0.5.0.dist-info/WHEEL
detamvc-0.5.0.dist-info/RECORD
