Metadata-Version: 2.1
Name: detamvc
Version: 0.5.0
Summary: 
Author: MBeebe
Author-email: grow.food.everywhere@gmail.com
Requires-Python: >=3.8,<4.0
Classifier: Programming Language :: Python :: 3
Classifier: Programming Language :: Python :: 3.8
Classifier: Programming Language :: Python :: 3.9
Classifier: Programming Language :: Python :: 3.10
Classifier: Programming Language :: Python :: 3.11
Requires-Dist: Jinja2 (>=3.1.2,<4.0.0)
Requires-Dist: authlib (>=1.2.0,<2.0.0)
Requires-Dist: deta (>=1.1.0,<2.0.0)
Requires-Dist: fastapi (>=0.78.0,<0.79.0)
Requires-Dist: httpx (>=0.23.1,<0.24.0)
Requires-Dist: itsdangerous (>=2.1.2,<3.0.0)
Requires-Dist: mkdocs-material (>=8.5.7,<9.0.0)
Requires-Dist: odetam (>=1.2.0,<2.0.0)
Requires-Dist: passlib[bcrypt] (>=1.7.4,<2.0.0)
Requires-Dist: pyjwt (>=2.6.0,<3.0.0)
Requires-Dist: python-dotenv (>=0.20.0,<0.21.0)
Requires-Dist: python-multipart (>=0.0.5,<0.0.6)
Requires-Dist: typer[all] (>=0.4.1,<0.5.0)
